contablo/__init__.py
contablo/cli.py
contablo/codes.py
contablo/csv_helper.py
contablo/csvimporter.py
contablo/csvtmplgen.py
contablo/fields.py
contablo/format_helpers.py
contablo/importable.py
contablo/importablemerge.py
contablo/importspec.py
contablo/match.py
contablo/numberformat.py
contablo-0.2.0.dist-info/LICENSE
contablo-0.2.0.dist-info/METADATA
contablo-0.2.0.dist-info/WHEEL
contablo-0.2.0.dist-info/entry_points.txt
contablo-0.2.0.dist-info/RECORD
