Metadata-Version: 2.1
Name: contablo
Version: 0.2.0
Summary: Configurable Table Loader package for python
Home-page: https://github.com/gandy92/contablo
License: MIT
Author: gandy92
Author-email: gandy92@googlemail.com
Requires-Python: >=3.10,<4.0
Classifier: Development Status :: 4 - Beta
Classifier: License :: OSI Approved :: MIT License
Classifier: Natural Language :: English
Classifier: Operating System :: OS Independent
Classifier: Programming Language :: Python :: 3
Classifier: Programming Language :: Python :: 3.10
Classifier: Programming Language :: Python :: 3.11
Classifier: Programming Language :: Python :: 3.12
Classifier: Programming Language :: Python :: 3.13
Requires-Dist: arithmetic-expressions (>=0.1,<0.2)
Requires-Dist: click (>=8.1.7,<9.0.0)
Requires-Dist: dateparser (>=1.2.0,<2.0.0)
Requires-Dist: iso3166 (>=2.1.1,<3.0.0)
Requires-Dist: pydantic (>=2.9.2,<3.0.0)
Requires-Dist: python-magic (>=0.4.27,<0.5.0)
Project-URL: Repository, https://github.com/gandy92/contablo
